algomatics/__init__.py
algomatics/arrays/__init__.py
algomatics/arrays/array.py
algomatics-0.0.0.dist-info/LICENSE
algomatics-0.0.0.dist-info/METADATA
algomatics-0.0.0.dist-info/WHEEL
algomatics-0.0.0.dist-info/top_level.txt
algomatics-0.0.0.dist-info/RECORD
