Metadata-Version: 2.1
Name: algomatics
Version: 0.0.0
Summary: This is one place tool for automating task
Author: vikash tripathi
License-File: LICENSE
